[
    {
        "initC": [
        0.0,
        0.0
        ],
        "autoX": 0,
        "autoY": 0,
        "XtoY": 0,
        "YtoX": 0
    },
    {
        "initC": [
        0.0,
        0.0
        ],
        "autoX": 0,
        "autoY": 0,
        "XtoY": 0,
        "YtoX": 1
    },
    [
        {
            "to": "X",
            "from": "X",
            "effect": -1
        },
        {
            "to": "Y",
            "from": "X",
            "effect": -1
        },
        {
            "to": "X",
            "from": "Y",
            "effect": -1
        },
        {
            "to": "Y",
            "from": "Y",
            "effect": -1
        }
    ]
]
Notes, X-autorepression motif