[
    {
        "NAME": "FP1",
        "TYPE": "OUTPUT",
        "m_halfLife": 7.484647748207417,
        "pB": 49.90713369498994,
        "p_halfLife": 41.46948290161341
    },
    {
        "NAME": "FP2",
        "TYPE": "OUTPUT",
        "m_halfLife": 5.026380883295012,
        "pB": 33.5048692743914,
        "p_halfLife": 6.349924723238651
    },
    {
        "NAME": "FP3",
        "TYPE": "OUTPUT",
        "m_halfLife": 9.865953752660527,
        "pB": 23.549608528181025,
        "p_halfLife": 25.77734941174524
    }
]